packages/__init__.py
packages/__main__.py
packages/data_input.py
packages/sorting.py
count_sort-1.0.dist-info/METADATA
count_sort-1.0.dist-info/WHEEL
count_sort-1.0.dist-info/top_level.txt
count_sort-1.0.dist-info/RECORD
