Metadata-Version: 2.1
Name: count-sort
Version: 1.0
Summary: Пакет для сортировки чисел методом подсчета
Home-page: UNKNOWN
Author: Шестера Дмитрий
Author-email: typa_lya@mail.ru
License: UNKNOWN
Platform: UNKNOWN
